codes/insmem.v
module IM(input [7:0] address,
          output reg [7:0] instruction);

    always @(*) begin

        case(address) //SAMPLE INSTRUCTION SET

            8'd0: instruction = 8'b00001010; //LDI A
            8'd1: instruction = 8'b01010011; //AND 3
            8'd2: instruction = 8'b01100100; //OR 4
            8'd3: instruction = 8'b01110111; //XOR 7
            8'd4: instruction = 8'b10000000; //NOT (A)
            8'd5: instruction = 8'b01000001; //SUB 1
            8'd6: instruction = 8'b10010000; //OUT

            default: instruction = 8'b00000000;

        endcase
    end

endmodule

codes/pc.v
module PC(input clk,
          input reset,
          input load,
          input inc,
          input [7:0] addr,
          output reg [7:0] pc_out);

    always @(posedge clk) begin

        if(reset) begin
            pc_out <= 8'd0;
        end

        else if(load) begin //LOAD
            pc_out <= addr;
        end
        
        else if(inc) begin //INCREMENT
            pc_out <= pc_out + 8'd1;
        end

    end

endmodule

tb/fetch_tb.v
`timescale 1ns/1ps

module fetch_tb;

reg clk;
reg reset;
reg inc;

wire [7:0] pc_out;
wire [7:0] instruction;

PC pc(.clk(clk),
      .reset(reset),
      .load(1'b0),
      .inc(inc),
      .addr(8'd0),
      .pc_out(pc_out));

IM im(.address(pc_out),
      .instruction(instruction));

    always #5 clk = ~clk;

    initial begin

        $dumpfile("fetch_dump.vcd");
        $dumpvars(0, fetch_tb);

        $monitor("TIME: %0t, PC ADDRESS: %d, INSTRUCTION: %b", $time, pc_out, instruction);

        clk = 1'b0;
        reset = 1'b1;
        inc = 1'b0;
        #10;

        reset = 1'b0;
        inc = 1'b1;
        #60;

        $finish;
    end

endmodule

simulation/fetch_dump.vcd
$date
	Fri Jun 19 15:56:58 2026
$end
$version
	Icarus Verilog
$end
$timescale
	1ps
$end
$scope module fetch_tb $end
$var wire 8 ! pc_out [7:0] $end
$var wire 8 " instruction [7:0] $end
$var reg 1 # clk $end
$var reg 1 $ inc $end
$var reg 1 % reset $end
$scope module im $end
$var wire 8 & address [7:0] $end
$var reg 8 ' instruction [7:0] $end
$upscope $end
$scope module pc $end
$var wire 8 ( addr [7:0] $end
$var wire 1 # clk $end
$var wire 1 $ inc $end
$var wire 1 ) load $end
$var wire 1 % reset $end
$var reg 8 * pc_out [7:0] $end
$upscope $end
$upscope $end
$enddefinitions $end
$comment Show the parameter values. $end
$dumpall
$end
#0
$dumpvars
bx *
0)
b0 (
bx '
bx &
1%
0$
0#
bx "
bx !
$end
#5000
b101 "
b101 '
b0 !
b0 &
b0 *
1#
#10000
0#
1$
0%
#15000
b100011 "
b100011 '
b1 !
b1 &
b1 *
1#
#20000
0#
#25000
b1000001 "
b1000001 '
b10 !
b10 &
b10 *
1#
#30000
0#
#35000
b10000000 "
b10000000 '
b11 !
b11 &
b11 *
1#
#40000
0#
#45000
b1100000 "
b1100000 '
b100 !
b100 &
b100 *
1#
#50000
0#
#55000
b0 "
b0 '
b101 !
b101 &
b101 *
1#
#60000
0#
#65000
b110 !
b110 &
b110 *
1#
