codes/pc.v
module PC(input clk,
          input reset,
          input load,
          input inc,
          input [7:0] addr,
          output reg [7:0] pc_out);

    always @(posedge clk) begin

        if(reset) begin
            pc_out <= 8'd0;
        end

        else if(load) begin //LOAD
            pc_out <= addr;
        end
        
        else if(inc) begin //INCREMENT
            pc_out <= pc_out + 8'd1;
        end

    end

endmodule

tb/pc_tb.v
`timescale 1ns/1ps

module pc_tb;

reg clk;
reg reset;
reg load;
reg inc;
reg [7:0] addr;

wire [7:0] pc_out;

PC uut(.clk(clk),
       .reset(reset),
       .load(load),
       .inc(inc),
       .addr(addr),
       .pc_out(pc_out));

    always #5 clk = ~clk;

    initial begin

        $dumpfile("pc_dump.vcd");
        $dumpvars(0, pc_tb);
        
        clk = 1'b0;
        reset = 1'b1;
        load = 1'b0;
        inc = 1'b0;
        addr = 8'd0;

        #10;
        reset = 1'b0;
        inc = 1'b1;

        #30;
        inc = 1'b0;
        addr = 8'd5;
        load = 1'b1;

        #10;
        load = 1'b0;
        inc = 1'b1;

        #20;

        $finish;
    end

endmodule

simulation/pc_dump.vcd
$date
	Wed Jun 17 15:16:44 2026
$end
$version
	Icarus Verilog
$end
$timescale
	1ps
$end
$scope module pc_tb $end
$var wire 8 ! pc_out [7:0] $end
$var reg 8 " addr [7:0] $end
$var reg 1 # clk $end
$var reg 1 $ inc $end
$var reg 1 % load $end
$var reg 1 & reset $end
$scope module uut $end
$var wire 8 ' addr [7:0] $end
$var wire 1 # clk $end
$var wire 1 $ inc $end
$var wire 1 % load $end
$var wire 1 & reset $end
$var reg 8 ( pc_out [7:0] $end
$upscope $end
$upscope $end
$enddefinitions $end
$comment Show the parameter values. $end
$dumpall
$end
#0
$dumpvars
bx (
b0 '
1&
0%
0$
0#
b0 "
bx !
$end
#5000
b0 !
b0 (
1#
#10000
0#
1$
0&
#15000
b1 !
b1 (
1#
#20000
0#
#25000
b10 !
b10 (
1#
#30000
0#
#35000
b11 !
b11 (
1#
#40000
0#
1%
b101 "
b101 '
0$
#45000
b101 !
b101 (
1#
#50000
0#
1$
0%
#55000
b110 !
b110 (
1#
#60000
0#
#65000
b111 !
b111 (
1#
